pyoracleclient/__init__.py
pyoracleclient/pyoracleclient.py
pyoracleclient/tns_template.py
pyoracleclient/res/icon.png
PyOracleClient-0.2.6.dist-info/LICENSE.txt
PyOracleClient-0.2.6.dist-info/METADATA
PyOracleClient-0.2.6.dist-info/WHEEL
PyOracleClient-0.2.6.dist-info/top_level.txt
PyOracleClient-0.2.6.dist-info/RECORD
