Metadata-Version: 2.1
Name: PyOracleClient
Version: 0.2.6
Summary: Oracle instant client binaries to be used together with cx_Oracle.
Home-page: https://github.com/LucaMingarelli/pyoracleclient
Author: Luca Mingarelli
Author-email: lucamingarelli@me.com
License: MIT
Classifier: Programming Language :: Python :: 3
Classifier: License :: OSI Approved :: MIT License
Classifier: Operating System :: OS Independent
Requires-Python: >=3.6
License-File: LICENSE.txt
Requires-Dist: tqdm
